{
  "parent": "botania:main/elf_portal_open",
  "criteria": {
    "air": {
      "conditions": {
        "items": [
          {
            "items": "botania:ender_air_bottle"
          }
        ]
      },
      "trigger": "minecraft:inventory_changed"
    }
  },
  "display": {
    "description": {
      "translate": "advancement.botania:enderAirMake.desc"
    },
    "icon": {
      "count": 1,
      "id": "botania:ender_air_bottle"
    },
    "title": {
      "translate": "advancement.botania:enderAirMake"
    }
  },
  "requirements": [
    [
      "air"
    ]
  ],
  "sends_telemetry_event": true
}